billzio_api/__init__.py
billzio_api/__version__.py
billzio_api/exceptions.py
billzio_api/handlers/__init__.py
billzio_api/handlers/async_handler.py
billzio_api/handlers/base.py
billzio_api/handlers/handler.py
billzio_api/models/auth.py
billzio_api/models/brands.py
billzio_api/models/categories.py
billzio_api/models/clients.py
billzio_api/models/currencies.py
billzio_api/models/orders.py
billzio_api/models/payment_types.py
billzio_api/models/products.py
billzio_api/models/shops.py
billzio_api-1.0.14.dist-info/LICENSE
billzio_api-1.0.14.dist-info/METADATA
billzio_api-1.0.14.dist-info/WHEEL
billzio_api-1.0.14.dist-info/RECORD
