Metadata-Version: 2.3
Name: billzio-api
Version: 1.0.14
Summary: Python wrapper for Billz.io Public API
License: Apache 2.0
Author: Sirojiddin Mustafayev
Requires-Python: >=3.9,<4.0
Classifier: License :: Other/Proprietary License
Classifier: Programming Language :: Python :: 3
Classifier: Programming Language :: Python :: 3.9
Classifier: Programming Language :: Python :: 3.10
Classifier: Programming Language :: Python :: 3.11
Classifier: Programming Language :: Python :: 3.12
Classifier: Programming Language :: Python :: 3.13
Requires-Dist: httpx (>=0.24.1,<0.25.0)
Requires-Dist: pydantic (>=2.1.1,<3.0.0)
